README.md
pyproject.toml
setup.py
Simple_Genetic_Algorithm/__init__.py
Simple_Genetic_Algorithm/simple_genetic_algorithm.py
Simple_Genetic_Algorithm.egg-info/PKG-INFO
Simple_Genetic_Algorithm.egg-info/SOURCES.txt
Simple_Genetic_Algorithm.egg-info/dependency_links.txt
Simple_Genetic_Algorithm.egg-info/requires.txt
Simple_Genetic_Algorithm.egg-info/top_level.txt