Metadata-Version: 2.4
Name: Simple_Genetic_Algorithm
Version: 0.2.5.0
Summary: Genetic Algorithm Framework
Home-page: https://github.com/M-106/Genetic-Algorithm
Download-URL: https://github.com/M-106/Genetic-Algorithm/archive/v_02.tar.gz
Author: Tobia Ippolito
License: MPL-2.0
Project-URL: Documentation, https://M-106.github.io/Genetic-Algorithm/
Project-URL: Source, https://github.com/M-106/Genetic-Algorithm
Keywords: Optimization,Genetic-Algorithm,Hyperparameter-Tuning
Classifier: Development Status :: 3 - Alpha
Classifier: Intended Audience :: Developers
Classifier: Topic :: Software Development :: Build Tools
Classifier: Programming Language :: Python :: 3.8
Classifier: Programming Language :: Python :: 3.9
Classifier: Programming Language :: Python :: 3.10
Classifier: Programming Language :: Python :: 3.11
Classifier: Programming Language :: Python :: 3.12
Requires-Dist: joblib
Dynamic: author
Dynamic: classifier
Dynamic: description
Dynamic: description-content-type
Dynamic: download-url
Dynamic: home-page
Dynamic: keywords
Dynamic: license
Dynamic: project-url
Dynamic: requires-dist
Dynamic: summary
